{
  "index_patterns": [ "logs-order-*" ],
  "aliases": {
    "logs-order-aliases": {}
  },
  "mappings": {
    "properties": {
      "Level": {
        "type": "text",
        "fields": {
          "keyword": {
            "type": "keyword",
            "ignore_above": 256
          }
        }
      },
      "MessageTemplate": {
        "type": "text",
        "fields": {
          "keyword": {
            "type": "keyword",
            "ignore_above": 256
          }
        }
      },
      "Properties": {
        "properties": {
          "AdditionalProperties": {
            "properties": {
              "CompanyInformationId": {
                "type": "long"
              },
              "CorrelationId": {
                "type": "text",
                "fields": {
                  "keyword": {
                    "type": "keyword",
                    "ignore_above": 256
                  }
                }
              },
              "Id": {
                "type": "text",
                "fields": {
                  "keyword": {
                    "type": "keyword",
                    "ignore_above": 256
                  }
                }
              },
              "IdentifyType": {
                "type": "text",
                "fields": {
                  "keyword": {
                    "type": "keyword",
                    "ignore_above": 256
                  }
                }
              },
              "LogType": {
                "type": "text",
                "fields": {
                  "keyword": {
                    "type": "keyword",
                    "ignore_above": 256
                  }
                }
              },
              "OrderIdentifier": {
                "type": "text",
                "fields": {
                  "keyword": {
                    "type": "keyword",
                    "ignore_above": 256
                  }
                }
              },
              "ProcessReference": {
                "type": "text",
                "fields": {
                  "keyword": {
                    "type": "keyword",
                    "ignore_above": 256
                  }
                }
              },
              "Source": {
                "type": "text",
                "fields": {
                  "keyword": {
                    "type": "keyword",
                    "ignore_above": 256
                  }
                }
              },
              "_typeTag": {
                "type": "text",
                "fields": {
                  "keyword": {
                    "type": "keyword",
                    "ignore_above": 256
                  }
                }
              }
            }
          },
          "Order": {
            "properties": {
              "CreatedAt": {
                "type": "date"
              },
              "Id": {
                "type": "long"
              },
              "Name": {
                "type": "text",
                "fields": {
                  "keyword": {
                    "type": "keyword",
                    "ignore_above": 256
                  }
                }
              },
              "NoteAttributes": {
                "properties": {
                  "Name": {
                    "type": "text",
                    "fields": {
                      "keyword": {
                        "type": "keyword",
                        "ignore_above": 256
                      }
                    }
                  },
                  "Value": {
                    "type": "text",
                    "fields": {
                      "keyword": {
                        "type": "keyword",
                        "ignore_above": 256
                      }
                    }
                  },
                  "_typeTag": {
                    "type": "text",
                    "fields": {
                      "keyword": {
                        "type": "keyword",
                        "ignore_above": 256
                      }
                    }
                  }
                }
              },
              "OrderNumber": {
                "type": "long"
              },
              "TaxLines": {
                "properties": {
                  "Price": {
                    "type": "text",
                    "fields": {
                      "keyword": {
                        "type": "keyword",
                        "ignore_above": 256
                      }
                    }
                  },
                  "Rate": {
                    "type": "float"
                  },
                  "Title": {
                    "type": "text",
                    "fields": {
                      "keyword": {
                        "type": "keyword",
                        "ignore_above": 256
                      }
                    }
                  },
                  "_typeTag": {
                    "type": "text",
                    "fields": {
                      "keyword": {
                        "type": "keyword",
                        "ignore_above": 256
                      }
                    }
                  }
                }
              },
              "TotalPrice": {
                "type": "text",
                "fields": {
                  "keyword": {
                    "type": "keyword",
                    "ignore_above": 256
                  }
                }
              },
              "TotalTax": {
                "type": "text",
                "fields": {
                  "keyword": {
                    "type": "keyword",
                    "ignore_above": 256
                  }
                }
              },
              "created_at": {
                "type": "date"
              },
              "discount_applications": {
                "properties": {
                  "Code": {
                    "type": "text",
                    "fields": {
                      "keyword": {
                        "type": "keyword",
                        "ignore_above": 256
                      }
                    }
                  },
                  "Description": {
                    "type": "text",
                    "fields": {
                      "keyword": {
                        "type": "keyword",
                        "ignore_above": 256
                      }
                    }
                  },
                  "TargetSelection": {
                    "type": "text",
                    "fields": {
                      "keyword": {
                        "type": "keyword",
                        "ignore_above": 256
                      }
                    }
                  },
                  "TargetType": {
                    "type": "text",
                    "fields": {
                      "keyword": {
                        "type": "keyword",
                        "ignore_above": 256
                      }
                    }
                  },
                  "Title": {
                    "type": "text",
                    "fields": {
                      "keyword": {
                        "type": "keyword",
                        "ignore_above": 256
                      }
                    }
                  },
                  "Type": {
                    "type": "text",
                    "fields": {
                      "keyword": {
                        "type": "keyword",
                        "ignore_above": 256
                      }
                    }
                  },
                  "Value": {
                    "type": "text",
                    "fields": {
                      "keyword": {
                        "type": "keyword",
                        "ignore_above": 256
                      }
                    }
                  },
                  "_typeTag": {
                    "type": "text",
                    "fields": {
                      "keyword": {
                        "type": "keyword",
                        "ignore_above": 256
                      }
                    }
                  }
                }
              },
              "discount_codes": {
                "properties": {
                  "_typeTag": {
                    "type": "text",
                    "fields": {
                      "keyword": {
                        "type": "keyword",
                        "ignore_above": 256
                      }
                    }
                  },
                  "amount": {
                    "type": "text",
                    "fields": {
                      "keyword": {
                        "type": "keyword",
                        "ignore_above": 256
                      }
                    }
                  },
                  "code": {
                    "type": "text",
                    "fields": {
                      "keyword": {
                        "type": "keyword",
                        "ignore_above": 256
                      }
                    }
                  },
                  "type": {
                    "type": "text",
                    "fields": {
                      "keyword": {
                        "type": "keyword",
                        "ignore_above": 256
                      }
                    }
                  }
                }
              },
              "id": {
                "type": "text",
                "fields": {
                  "keyword": {
                    "type": "keyword",
                    "ignore_above": 256
                  }
                }
              },
              "name": {
                "type": "text",
                "fields": {
                  "keyword": {
                    "type": "keyword",
                    "ignore_above": 256
                  }
                }
              },
              "note_attributes": {
                "properties": {
                  "_typeTag": {
                    "type": "text",
                    "fields": {
                      "keyword": {
                        "type": "keyword",
                        "ignore_above": 256
                      }
                    }
                  },
                  "name": {
                    "type": "text",
                    "fields": {
                      "keyword": {
                        "type": "keyword",
                        "ignore_above": 256
                      }
                    }
                  },
                  "value": {
                    "type": "text",
                    "fields": {
                      "keyword": {
                        "type": "keyword",
                        "ignore_above": 256
                      }
                    }
                  }
                }
              },
              "order_number": {
                "type": "text",
                "fields": {
                  "keyword": {
                    "type": "keyword",
                    "ignore_above": 256
                  }
                }
              },
              "tax_lines": {
                "properties": {
                  "_typeTag": {
                    "type": "text",
                    "fields": {
                      "keyword": {
                        "type": "keyword",
                        "ignore_above": 256
                      }
                    }
                  },
                  "price": {
                    "type": "text",
                    "fields": {
                      "keyword": {
                        "type": "keyword",
                        "ignore_above": 256
                      }
                    }
                  },
                  "rate": {
                    "type": "text",
                    "fields": {
                      "keyword": {
                        "type": "keyword",
                        "ignore_above": 256
                      }
                    }
                  },
                  "title": {
                    "type": "text",
                    "fields": {
                      "keyword": {
                        "type": "keyword",
                        "ignore_above": 256
                      }
                    }
                  }
                }
              },
              "total_price": {
                "type": "text",
                "fields": {
                  "keyword": {
                    "type": "keyword",
                    "ignore_above": 256
                  }
                }
              },
              "total_tax": {
                "type": "text",
                "fields": {
                  "keyword": {
                    "type": "keyword",
                    "ignore_above": 256
                  }
                }
              },
              "updated_at": {
                "type": "date"
              }
            }
          }
        }
      },
      "RenderedMessage": {
        "type": "text",
        "fields": {
          "keyword": {
            "type": "keyword",
            "ignore_above": 256
          }
        }
      },
      "Timestamp": {
        "type": "date"
      }
    }
  },
  "settings": {
    "index": {
      "number_of_shards": "5",
      "blocks": {
        "read_only_allow_delete": "false",
        "write": "false"
      },
      "number_of_replicas": "1"
    }
  }
}